devlogs/__init__.py
devlogs/__main__.py
devlogs/build_info.py
devlogs/cli.py
devlogs/config.py
devlogs/context.py
devlogs/demo.py
devlogs/devlogs_client.py
devlogs/formatting.py
devlogs/handler.py
devlogs/levels.py
devlogs/retention.py
devlogs/scrub.py
devlogs/time_utils.py
devlogs/version.py
devlogs/wrapper.py
devlogs/collector/__init__.py
devlogs/collector/auth.py
devlogs/collector/cli.py
devlogs/collector/errors.py
devlogs/collector/forwarder.py
devlogs/collector/ingestor.py
devlogs/collector/schema.py
devlogs/collector/server.py
devlogs/jenkins/__init__.py
devlogs/jenkins/cli.py
devlogs/jenkins/core.py
devlogs/mcp/__init__.py
devlogs/mcp/server.py
devlogs/opensearch/__init__.py
devlogs/opensearch/client.py
devlogs/opensearch/indexing.py
devlogs/opensearch/mappings.py
devlogs/opensearch/queries.py
devlogs/web/__init__.py
devlogs/web/server.py
devlogs/web/static/devlogs.css
devlogs/web/static/devlogs.js
devlogs/web/static/index.html
devlogs-2.0.3.dist-info/licenses/LICENSE
devlogs-2.0.3.dist-info/METADATA
devlogs-2.0.3.dist-info/WHEEL
devlogs-2.0.3.dist-info/entry_points.txt
devlogs-2.0.3.dist-info/top_level.txt
devlogs-2.0.3.dist-info/RECORD
