Metadata-Version: 2.4
Name: devlogs
Version: 2.0.3
Summary: Developer-focused logging library for Python with OpenSearch integration.
Author-email: Dan Driscoll <dan@thedandriscoll.org>
License: MIT License
Requires-Python: >=3.11
License-File: LICENSE
Requires-Dist: opensearch-py>=2.4.0
Requires-Dist: click>=8.1.0
Requires-Dist: typer>=0.9.0
Requires-Dist: fastapi>=0.110.0
Requires-Dist: uvicorn>=0.24.0
Requires-Dist: python-dotenv>=1.0.0
Requires-Dist: mcp>=1.0.0
Provides-Extra: dev
Requires-Dist: httpx>=0.26.0; extra == "dev"
Requires-Dist: pytest>=8.0.0; extra == "dev"
Requires-Dist: pytest-asyncio>=0.23.0; extra == "dev"
Dynamic: license-file
